odoo/addons/sale_report_delivered_attribute_values/README.rst
odoo/addons/sale_report_delivered_attribute_values/__init__.py
odoo/addons/sale_report_delivered_attribute_values/__manifest__.py
odoo/addons/sale_report_delivered_attribute_values/i18n/es.po
odoo/addons/sale_report_delivered_attribute_values/i18n/it.po
odoo/addons/sale_report_delivered_attribute_values/i18n/sale_report_delivered_attribute_values.pot
odoo/addons/sale_report_delivered_attribute_values/readme/CONTEXT.md
odoo/addons/sale_report_delivered_attribute_values/readme/CONTRIBUTORS.md
odoo/addons/sale_report_delivered_attribute_values/readme/CREDITS.md
odoo/addons/sale_report_delivered_attribute_values/readme/DESCRIPTION.md
odoo/addons/sale_report_delivered_attribute_values/readme/USAGE.md
odoo/addons/sale_report_delivered_attribute_values/report/__init__.py
odoo/addons/sale_report_delivered_attribute_values/report/sale_report.py
odoo/addons/sale_report_delivered_attribute_values/static/description/icon.png
odoo/addons/sale_report_delivered_attribute_values/static/description/index.html
odoo/addons/sale_report_delivered_attribute_values/tests/__init__.py
odoo/addons/sale_report_delivered_attribute_values/tests/test_sale_report_delivered_attribute_values.py
odoo/addons/sale_report_delivered_attribute_values/views/sale_report_delivered_views.xml
odoo_addon_sale_report_delivered_attribute_values-16.0.1.0.1.3.dist-info/METADATA
odoo_addon_sale_report_delivered_attribute_values-16.0.1.0.1.3.dist-info/WHEEL
odoo_addon_sale_report_delivered_attribute_values-16.0.1.0.1.3.dist-info/top_level.txt
odoo_addon_sale_report_delivered_attribute_values-16.0.1.0.1.3.dist-info/RECORD
