Metadata-Version: 2.1
Name: odoo-addon-sale_report_delivered_attribute_values
Version: 16.0.1.0.1.3
Summary: Allow to view Attribute values of Lines on Sale Report Delivered
Home-page: https://github.com/OCA/sale-reporting
Author: Moduon, Odoo Community Association (OCA)
Author-email: support@odoo-community.org
License: AGPL-3
Classifier: Programming Language :: Python
Classifier: Framework :: Odoo
Classifier: Framework :: Odoo :: 16.0
Classifier: License :: OSI Approved :: GNU Affero General Public License v3
Classifier: Development Status :: 3 - Alpha
Requires-Python: >=3.10
Requires-Dist: odoo-addon-sale-order-line-product-attribute-values<16.1dev,>=16.0dev
Requires-Dist: odoo-addon-sale-report-delivered<16.1dev,>=16.0dev
Requires-Dist: odoo<16.1dev,>=16.0a
